pircpy/__init__.py
Pircpy-1.0.dist-info/LICENSE.txt
Pircpy-1.0.dist-info/METADATA
Pircpy-1.0.dist-info/WHEEL
Pircpy-1.0.dist-info/top_level.txt
Pircpy-1.0.dist-info/RECORD
