Metadata-Version: 2.1
Name: Pircpy
Version: 1.0
Summary: Python wrapper Library for Pickering PIRC API
Home-page: 
Author: Pickering Interfaces
Author-email: Pickering Interfaces <support@pickeringtest.com>
License: Copyright (c) 2017-2024 Pickering Interfaces Ltd.
Project-URL: homepage, https://downloads.pickeringtest.info/downloads/RelayCountingApplication/
License-File: LICENSE.txt
Requires-Dist: enum34
